lake/__init__.py
lake/etc.py
lake/array/__init__.py
lake/array/array_.py
lake/array/count_next_interface.py
lake/array/iterator_pair.py
lake/array/ring_buffer.py
lake/array/ring_buffer_container.py
lake/array/sample_.py
lake/array/shuffler.py
lake/array/split.py
lake/data/__init__.py
lake/data/db_class.py
lake/data/mc.py
lake/data/mysql.py
lake/decorator/__init__.py
lake/decorator/cache.py
lake/decorator/decorator_args.py
lake/decorator/decorator_logging.py
lake/decorator/decorator_mem_usage.py
lake/decorator/decorator_more_try.py
lake/decorator/decorator_singleton.py
lake/decorator/decorator_time.py
lake/dic/__init__.py
lake/dic/dic_op.py
lake/dir/__init__.py
lake/dir/dir_loop.py
lake/dir/dir_op.py
lake/file/__init__.py
lake/file/file_add.py
lake/file/file_op.py
lake/file/file_pkg.py
lake/file/file_read.py
lake/file/file_write.py
lake/image/__init__.py
lake/image/image_numpy_op.py
lake/image/image_pil_op.py
lake/mt/__init__.py
lake/mt/math_fun.py
lake/mt/math_op.py
lake/network/__init__.py
lake/network/downloader.py
lake/network/proxy.py
lake/nlp/__init__.py
lake/nlp/abbr.py
lake/nlp/nltk_.py
lake/nlp/tag_deps_data.py
lake/np/__init__.py
lake/option/__init__.py
lake/option/base_option.py
lake/option/nn_option.py
lake/option/optionParser.py
lake/shell/__init__.py
lake/string/__init__.py
lake/string/color.py
lake/tf/__init__.py
lake/tf/loss.py
lake/thread/__init__.py
lake/tm/__init__.py
lake/tm/time_out.py
lake/torch/__init__.py
lake/torch/data_interface.py
lake/torch/torch_helper.py
lake/torch/trainer.py
lake/torch/network/__init__.py
lake/torch/network/base.py
lake/torch/network/cnn.py
lake/torch/network/instance_normalization.py
lake/torch/network/resnet.py
lake/torch/network/unet.py
lake/torch/optim/__init__.py
lake/torch/optim/shared_adam.py
lake/torch/utils/__init__.py
lake/torch/utils/image.py
lake/torch/utils/image_folder.py
lake/torch/utils/learning_rator.py
lake-1.0.1.dist-info/DESCRIPTION.rst
lake-1.0.1.dist-info/METADATA
lake-1.0.1.dist-info/RECORD
lake-1.0.1.dist-info/WHEEL
lake-1.0.1.dist-info/metadata.json
lake-1.0.1.dist-info/top_level.txt
