Metadata-Version: 2.0
Name: lake
Version: 1.0.1
Summary: a python lib for network, file, and something else
Home-page: https://github.com/CosmosShadow/lake
Author: lichen
Author-email: lichenarthurdata@gmail.com
License: MIT License
Keywords: lake
Platform: any
